zeit/nightwatch/__init__.py
zeit/nightwatch/gcs.py
zeit/nightwatch/jsonreport.py
zeit/nightwatch/playwright.py
zeit/nightwatch/prometheus.py
zeit/nightwatch/pytest.py
zeit/nightwatch/requests.py
zeit_nightwatch-2.3.2.dist-info/METADATA
zeit_nightwatch-2.3.2.dist-info/WHEEL
zeit_nightwatch-2.3.2.dist-info/entry_points.txt
zeit_nightwatch-2.3.2.dist-info/licenses/LICENSE
zeit_nightwatch-2.3.2.dist-info/RECORD
