Metadata-Version: 2.3
Name: zeit.nightwatch
Version: 2.3.2
Summary: pytest helpers for http smoke tests
Project-URL: Repository, https://github.com/ZeitOnline/zeit.nightwatch
Author-email: Zeit Online <zon-backend@zeit.de>
Requires-Dist: cssselect
Requires-Dist: google-cloud-storage
Requires-Dist: junit2html
Requires-Dist: junitparser
Requires-Dist: lxml
Requires-Dist: mechanicalsoup
Requires-Dist: prometheus-client
Requires-Dist: pytest
Requires-Dist: pytest-playwright
Requires-Dist: requests
